sedipack/__init__.py
sedipack/grainpreprocess.py
sedipack/grainstats.py
sedipack/grainstatsdata.py
sedipack/grainviz.py
sedipack-0.0.6.2.dist-info/LICENSE
sedipack-0.0.6.2.dist-info/METADATA
sedipack-0.0.6.2.dist-info/WHEEL
sedipack-0.0.6.2.dist-info/top_level.txt
sedipack-0.0.6.2.dist-info/RECORD
