Metadata-Version: 2.1
Name: sedipack
Version: 0.0.6.2
Summary: A Sedimentology package for Grain Statistics and Plots.
Home-page: https://github.com/philip-kio/SediPack
Author: Philip Ireoluwa Okiokio
Author-email: philipokiokio@gmail.com
License: UNKNOWN
Platform: UNKNOWN
Classifier: Programming Language :: Python :: 3
Classifier: License :: OSI Approved :: MIT License
Classifier: Operating System :: OS Independent
Requires-Python: >=3.6
Requires-Dist: matplotlib
Requires-Dist: pandas
Requires-Dist: numpy
